setup.py
WeixunSDKCore.egg-info/PKG-INFO
WeixunSDKCore.egg-info/SOURCES.txt
WeixunSDKCore.egg-info/dependency_links.txt
WeixunSDKCore.egg-info/top_level.txt
weixunsdkcore/__init__.py
weixunsdkcore/client.py
weixunsdkcore/helper.py
weixunsdkcore/request.py
weixunsdkcore/signature.py