Metadata-Version: 1.1
Name: WeixunSDKCore
Version: 0.1.20170214.1549
Summary: WeixunSDKCore
Home-page: http://github.com/weixunsdkcore
Author: Maple Liu
Author-email: maple.liu@microfastup.com
License: Apache License, Version 2.0
Platform: UNKNOWN
Classifier: Development Status :: 3 - Alpha
Classifier: Environment :: Web Environment
Classifier: Intended Audience :: Developers
Classifier: Operating System :: OS Independent
Classifier: Programming Language :: Python
